tensorstore/LICENSE
tensorstore/__init__.pyi
tensorstore/ocdbt.pyi
tensorstore/__init__.py
tensorstore/_tensorstore.cpython-314t-darwin.so
tensorstore-0.1.79.dist-info/RECORD
tensorstore-0.1.79.dist-info/WHEEL
tensorstore-0.1.79.dist-info/top_level.txt
tensorstore-0.1.79.dist-info/METADATA
tensorstore-0.1.79.dist-info/licenses/LICENSE
tensorstore-0.1.79.dist-info/licenses/AUTHORS
