Metadata-Version: 2.4
Name: tensorstore
Version: 0.1.79
Summary: Read and write large, multi-dimensional arrays
Author-email: TensorStore Team <tensorstore-team@google.com>
License-Expression: Apache-2.0
Project-URL: Repository, https://github.com/google/tensorstore
Project-URL: Issues, https://github.com/google/tensorstore/issues
Project-URL: Documentation, https://google.github.io/tensorstore
Classifier: Development Status :: 5 - Production/Stable
Classifier: Topic :: Software Development :: Libraries
Requires-Python: >=3.11
License-File: LICENSE
License-File: AUTHORS
Requires-Dist: numpy>=1.22.0
Requires-Dist: ml_dtypes>=0.5.0
Dynamic: license-file
